{"_path":"/certificate/2018-10-30_treinaweb_facebook_marketing_como_colocar_sua_empresa_no_facebook","_draft":false,"_partial":false,"_locale":"en","_empty":false,"title":"Facebook Marketing Como colocar sua empresa no Facebook","description":"","excerpt":{"type":"root","children":[{"type":"element","tag":"code","props":{"code":"                                         Geraldo Luis da Silva Ribeiro\n                                                 portador(a) do CPF\n                                                055.593.028-99\n                                             participou e concluiu o curso\n                          Facebook Marketing - Como colocar sua empresa no facebook\n   com carga horária de                                                                   no período de\n   4 horas                                                                   30/10/2018 a 27/04/2020\n\n\n\n\nCódigo: HAQEVRYSBTKK\n\f\n"},"children":[{"type":"element","tag":"pre","props":{},"children":[{"type":"element","tag":"code","props":{"__ignoreMap":""},"children":[{"type":"text","value":"                                         Geraldo Luis da Silva Ribeiro\n                                                 portador(a) do CPF\n                                                055.593.028-99\n                                             participou e concluiu o curso\n                          Facebook Marketing - Como colocar sua empresa no facebook\n   com carga horária de                                                                   no período de\n   4 horas                                                                   30/10/2018 a 27/04/2020\n\n\n\n\nCódigo: HAQEVRYSBTKK\n\f\n"}]}]}]}]},"id":"b7167a99","tags":["marketing","facebook"],"date":"2018-10-30","miniImage":"/certificate/b7167a99.png","miniImageWidth":600,"miniImageHeight":424,"largeImage":"/certificate/b7167a99-L.png","largeImageWidth":1280,"largeImageHeight":905,"school":"treinaweb","schoolColor":"bg-indigo-500 text-white","inIssueYear":2018,"inIssueMonth":10,"inOrganizationName":"Treinaweb","inOrganizationUrl":"","body":{"type":"root","children":[{"type":"element","tag":"code","props":{"code":"                                         Geraldo Luis da Silva Ribeiro\n                                                 portador(a) do CPF\n                                                055.593.028-99\n                                             participou e concluiu o curso\n                          Facebook Marketing - Como colocar sua empresa no facebook\n   com carga horária de                                                                   no período de\n   4 horas                                                                   30/10/2018 a 27/04/2020\n\n\n\n\nCódigo: HAQEVRYSBTKK\n\f\n"},"children":[{"type":"element","tag":"pre","props":{},"children":[{"type":"element","tag":"code","props":{"__ignoreMap":""},"children":[{"type":"element","tag":"span","props":{"class":"line"},"children":[{"type":"element","tag":"span","props":{},"children":[{"type":"text","value":"                                         Geraldo Luis da Silva Ribeiro\n                                                 portador(a) do CPF\n                                                055.593.028-99\n                                             participou e concluiu o curso\n                          Facebook Marketing - Como colocar sua empresa no facebook\n   com carga horária de                                                                   no período de\n   4 horas                                                                   30/10/2018 a 27/04/2020\n\n\n\n\nCódigo: HAQEVRYSBTKK\n\f"}]}]}]}]}]}],"toc":{"title":"","searchDepth":2,"depth":2,"links":[]}},"_type":"markdown","_id":"content:certificate:2018-10-30_treinaweb_Facebook_Marketing_Como_colocar_sua_empresa_no_Facebook.md","_source":"content","_file":"certificate/2018-10-30_treinaweb_Facebook_Marketing_Como_colocar_sua_empresa_no_Facebook.md","_extension":"md"}