{"_path":"/til/lxc","_draft":false,"_partial":false,"_locale":"en","_empty":false,"title":"LXC - Linux Container","description":"","excerpt":{"type":"root","children":[{"type":"element","tag":"h2","props":{"id":"how-to-install-lxd"},"children":[{"type":"text","value":"How to install LXD"}]},{"type":"element","tag":"code","props":{"code":"apt install snap\nsnap install lxd\n","language":"bash"},"children":[{"type":"element","tag":"pre","props":{},"children":[{"type":"element","tag":"code","props":{"__ignoreMap":""},"children":[{"type":"text","value":"apt install snap\nsnap install lxd\n"}]}]}]},{"type":"element","tag":"p","props":{},"children":[{"type":"element","tag":"a","props":{"href":"http://www.panticz.de/lxd","rel":["nofollow"]},"children":[{"type":"text","value":"http://www.panticz.de/lxd"}]}]},{"type":"element","tag":"h2","props":{"id":"features"},"children":[{"type":"text","value":"Features"}]},{"type":"element","tag":"ul","props":{},"children":[{"type":"element","tag":"li","props":{},"children":[{"type":"text","value":"device pass-through capabilities"},{"type":"element","tag":"ul","props":{},"children":[{"type":"element","tag":"li","props":{},"children":[{"type":"text","value":"assign hardware directly to the lxc containers"}]}]}]},{"type":"element","tag":"li","props":{},"children":[{"type":"text","value":"network and storage management capabilities"},{"type":"element","tag":"ul","props":{},"children":[{"type":"element","tag":"li","props":{},"children":[{"type":"text","value":"storage pooling"}]}]}]},{"type":"element","tag":"li","props":{},"children":[{"type":"text","value":"snapshot of running container"}]},{"type":"element","tag":"li","props":{},"children":[{"type":"text","value":"live migration of running containers between hosts"}]},{"type":"element","tag":"li","props":{},"children":[{"type":"text","value":"LXD can also integrate with cloud platform, such OpenStack"}]},{"type":"element","tag":"li","props":{},"children":[{"type":"text","value":"improved control over compute resources"}]},{"type":"element","tag":"li","props":{},"children":[{"type":"text","value":"clustering"}]}]}]},"date":"2022-09-05T00:00:00.000Z","tags":["lxc","linux","container"],"body":{"type":"root","children":[{"type":"element","tag":"h2","props":{"id":"how-to-install-lxd"},"children":[{"type":"text","value":"How to install LXD"}]},{"type":"element","tag":"code","props":{"code":"apt install snap\nsnap install lxd\n","language":"bash"},"children":[{"type":"element","tag":"pre","props":{},"children":[{"type":"element","tag":"code","props":{"__ignoreMap":""},"children":[{"type":"element","tag":"span","props":{"class":"line"},"children":[{"type":"element","tag":"span","props":{"class":"ct-5f51b2"},"children":[{"type":"text","value":"apt install snap"}]}]},{"type":"element","tag":"span","props":{"class":"line"},"children":[{"type":"element","tag":"span","props":{"class":"ct-5f51b2"},"children":[{"type":"text","value":"snap install lxd"}]}]}]}]}]},{"type":"element","tag":"p","props":{},"children":[{"type":"element","tag":"a","props":{"href":"http://www.panticz.de/lxd","rel":["nofollow"]},"children":[{"type":"text","value":"http://www.panticz.de/lxd"}]}]},{"type":"element","tag":"h2","props":{"id":"features"},"children":[{"type":"text","value":"Features"}]},{"type":"element","tag":"ul","props":{},"children":[{"type":"element","tag":"li","props":{},"children":[{"type":"text","value":"device pass-through capabilities"},{"type":"element","tag":"ul","props":{},"children":[{"type":"element","tag":"li","props":{},"children":[{"type":"text","value":"assign hardware directly to the lxc containers"}]}]}]},{"type":"element","tag":"li","props":{},"children":[{"type":"text","value":"network and storage management capabilities"},{"type":"element","tag":"ul","props":{},"children":[{"type":"element","tag":"li","props":{},"children":[{"type":"text","value":"storage pooling"}]}]}]},{"type":"element","tag":"li","props":{},"children":[{"type":"text","value":"snapshot of running container"}]},{"type":"element","tag":"li","props":{},"children":[{"type":"text","value":"live migration of running containers between hosts"}]},{"type":"element","tag":"li","props":{},"children":[{"type":"text","value":"LXD can also integrate with cloud platform, such OpenStack"}]},{"type":"element","tag":"li","props":{},"children":[{"type":"text","value":"improved control over compute resources"}]},{"type":"element","tag":"li","props":{},"children":[{"type":"text","value":"clustering"}]}]},{"type":"element","tag":"style","children":[{"type":"text","value":".ct-5f51b2{color:#F8F8F2}"}]}],"toc":{"title":"","searchDepth":2,"depth":2,"links":[{"id":"how-to-install-lxd","depth":2,"text":"How to install LXD"},{"id":"features","depth":2,"text":"Features"}]}},"_type":"markdown","_id":"content:til:lxc.md","_source":"content","_file":"til/lxc.md","_extension":"md"}